tab_cli/__init__.py
tab_cli/cli.py
tab_cli/config.py
tab_cli/style.py
tab_cli/url_parser.py
tab_cli/formats/__init__.py
tab_cli/formats/avro.py
tab_cli/formats/base.py
tab_cli/formats/csv.py
tab_cli/formats/jsonl.py
tab_cli/formats/parquet.py
tab_cli/handlers/__init__.py
tab_cli/handlers/base.py
tab_cli/handlers/cli_table.py
tab_cli/storage/__init__.py
tab_cli/storage/aws.py
tab_cli/storage/az.py
tab_cli/storage/base.py
tab_cli/storage/fsspec.py
tab_cli/storage/gcloud.py
tab_cli/storage/local.py
tab_cli-0.1.1.dist-info/METADATA
tab_cli-0.1.1.dist-info/WHEEL
tab_cli-0.1.1.dist-info/entry_points.txt
tab_cli-0.1.1.dist-info/licenses/LICENSE
tab_cli-0.1.1.dist-info/RECORD
